ICECREAM/__init__.py
ICECREAM/baseapp.py
ICECREAM/cache.py
ICECREAM/core_manager.py
ICECREAM/db_initializer.py
ICECREAM/file_handler.py
ICECREAM/filters.py
ICECREAM/http.py
ICECREAM/makeproject.py
ICECREAM/paginator.py
ICECREAM/plugin.py
ICECREAM/rbac.py
ICECREAM/status.py
ICECREAM/test.py
ICECREAM/util.py
ICECREAM/validators.py
ICECREAM/wrappers.py
ICECREAM/api_cache/__init__.py
ICECREAM/api_cache/backend.py
ICECREAM/api_cache/bases.py
ICECREAM/api_cache/plugin.py
ICECREAM/assets/__init__.py
ICECREAM/assets/project_assets.zip
ICECREAM/migration_tool/__init__.py
ICECREAM/migration_tool/env.py
ICECREAM/models/__init__.py
ICECREAM/models/basemodels.py
ICECREAM/models/query.py
ICECREAM/statics/__init__.py
ICECREAM/statics/images/ice.png
ICECREAM/statics/templates/index.html
icecreamy-0.0.6.4.2.data/scripts/make_project.py
icecreamy-0.0.6.4.2.dist-info/LICENSE
icecreamy-0.0.6.4.2.dist-info/METADATA
icecreamy-0.0.6.4.2.dist-info/WHEEL
icecreamy-0.0.6.4.2.dist-info/entry_points.txt
icecreamy-0.0.6.4.2.dist-info/top_level.txt
icecreamy-0.0.6.4.2.dist-info/RECORD
