Metadata-Version: 2.1
Name: icecreamy
Version: 0.0.6.4.2
Summary: restful framework with bottle
Home-page: https://github.com/xenups/ICECREAM
Author: xenups
Author-email: xenups@gmail.com
License: LICENSE.txt
Platform: UNKNOWN
License-File: LICENSE
Requires-Dist: bottle-jwt2 (==0.16)
Requires-Dist: alembic
Requires-Dist: appdirs
Requires-Dist: bottle
Requires-Dist: codecov
Requires-Dist: coverage
Requires-Dist: gunicorn
Requires-Dist: Jinja2
Requires-Dist: jsonschema
Requires-Dist: marshmallow
Requires-Dist: mongosql
Requires-Dist: nose
Requires-Dist: psycopg2-binary
Requires-Dist: PyJWT
Requires-Dist: python-dateutil
Requires-Dist: python-dotenv
Requires-Dist: python-throttle
Requires-Dist: ratelimit
Requires-Dist: redis
Requires-Dist: rootpath
Requires-Dist: sentry-sdk
Requires-Dist: simplerbac
Requires-Dist: sqla-wrapper
Requires-Dist: sqlacodegen
Requires-Dist: SQLAlchemy (==1.4.11)
Requires-Dist: SQLAlchemy-Searchable
Requires-Dist: SQLAlchemy-Utils (==0.37.0)
Requires-Dist: tornado
Requires-Dist: tox
Requires-Dist: WebTest
Requires-Dist: sqlalchemy-filters
Requires-Dist: Werkzeug
Requires-Dist: ujson
